SPART/BSM.py
SPART/PROSPECT_5D.py
SPART/SAILH.py
SPART/SMAC.py
SPART/SPART.py
SPART/__init__.py
SPART/model_parameters/ET_irradiance.pkl
SPART/model_parameters/optical_params.pkl
SPART/sensor_information/LANDSAT4-TM.pkl
SPART/sensor_information/LANDSAT5-TM.pkl
SPART/sensor_information/LANDSAT7-ETM.pkl
SPART/sensor_information/LANDSAT8-OLI.pkl
SPART/sensor_information/Sentinel3A-OLCI.pkl
SPART/sensor_information/Sentinel3B-OLCI.pkl
SPART/sensor_information/TerraAqua-MODIS.pkl
SPART_python-1.0.9.dist-info/LICENSE
SPART_python-1.0.9.dist-info/METADATA
SPART_python-1.0.9.dist-info/WHEEL
SPART_python-1.0.9.dist-info/top_level.txt
SPART_python-1.0.9.dist-info/RECORD
