Metadata-Version: 2.1
Name: SPART-python
Version: 1.0.9
Summary: Python implementation of the SPART optical radiative transfer model.
Home-page: https://github.com/wirrell/SPART-python
Author: G. Worrall
Author-email: worrall.george@gmail.com
License: UNKNOWN
Platform: UNKNOWN
Classifier: Programming Language :: Python :: 3
Classifier: License :: OSI Approved :: GNU General Public License v3 (GPLv3)
Classifier: Operating System :: OS Independent
Classifier: Topic :: Scientific/Engineering :: GIS
Requires-Python: >=3.4
Requires-Dist: numpy (==1.18.5)
Requires-Dist: pandas (==1.0.5)
Requires-Dist: scipy (==1.5.0)
